form_validator/__init__.py
form_validator/validator.py
form_validator-1.4.0.dist-info/licenses/LICENSE
tests/__init__.py
tests/test_validator.py
form_validator-1.4.0.dist-info/METADATA
form_validator-1.4.0.dist-info/WHEEL
form_validator-1.4.0.dist-info/top_level.txt
form_validator-1.4.0.dist-info/RECORD
