Metadata-Version: 2.4
Name: form-validator
Version: 1.4.0
Summary: A Python package for validating forms.
Home-page: https://github.com/your_username/form-validator
Author: Jaswanth Krishna Perla
Author-email: perlajaswanthkrishna@gmail.com
License: MIT
Classifier: Programming Language :: Python :: 3
Classifier: License :: OSI Approved :: MIT License
Classifier: Operating System :: OS Independent
Requires-Python: >=3.6
License-File: LICENSE
Dynamic: license-file
